{
  "datasetId": "coastline_cia",
  "title": "Coastline Length",
  "year": "N/A (geographic constant)",
  "source": "CIA World Factbook",
  "unit": "km",
  "higherIsBetter": true,
  "values": {
    "JP": 29751,
    "BR": 7491,
    "ID": 54716,
    "VN": 3444,
    "ET": 0,
    "CO": 3208,
    "US": 19924,
    "CN": 14500,
    "IN": 7000,
    "NO": 25148,
    "KE": 536,
    "CH": 0,
    "AU": 25760,
    "EG": 2450,
    "MX": 9330,
    "NL": 451,
    "PH": 36289,
    "IS": 4970,
    "CL": 6435,
    "SA": 2640,
    "TR": 7200,
    "NZ": 15134,
    "DE": 2389,
    "NG": 853
  }
}
